tflstatuscli/__init__.py
tflstatuscli/tflstatuscli.py
tflstatuscli-0.1.5.dist-info/METADATA
tflstatuscli-0.1.5.dist-info/WHEEL
tflstatuscli-0.1.5.dist-info/entry_points.txt
tflstatuscli-0.1.5.dist-info/RECORD
